{"chunk_definitions":[{"row":34,"row_count":1,"visible":true,"expansion_state":0,"options":{"engine":"r","label":"setup","include":false},"document_id":"0BAE39E7","chunk_id":"csetup_chunk","chunk_label":"setup"},{"row":158,"row_count":1,"visible":true,"expansion_state":0,"options":{"engine":"r","label":"functions","include":false},"document_id":"0BAE39E7","chunk_id":"c330ox8j54o8o","chunk_label":"functions"},{"row":287,"row_count":1,"visible":true,"expansion_state":0,"options":{"engine":"r","label":"data","include":false},"document_id":"0BAE39E7","chunk_id":"cgf04twhwd6ia","chunk_label":"data"},{"row":362,"row_count":1,"visible":true,"expansion_state":0,"options":{"engine":"r","label":"consumption_data_and_rates","echo":false,"warning":false,"include":false},"document_id":"0BAE39E7","chunk_id":"c39dh5bayws6d","chunk_label":"consumption_data_and_rates"},{"row":460,"row_count":1,"visible":true,"expansion_state":0,"options":{"engine":"r","label":"exclusions","include":false},"document_id":"0BAE39E7","chunk_id":"czbggaphjptzy","chunk_label":"exclusions"},{"row":510,"row_count":1,"visible":true,"expansion_state":0,"options":{"engine":"r","label":"all_countries_trend_ghg","echo":false,"warning":false,"fig.width":12,"fig.height":14,"dpi":300,"fig.path":"../../Results/Plots/Decarbonising countries/","dev":["png","pdf"]},"document_id":"0BAE39E7","chunk_id":"cgg70nou85xt8","chunk_label":"all_countries_trend_ghg"}],"doc_write_time":1688550140,"working_dir":null,"default_chunk_options":{"echo":false},"chunk_rendered_width":700}